leo_1c/__init__.py
leo_1c/client.py
leo_1c/connection.py
leo_1c/exception.py
leo_1c/odata_resource.py
leo_1c/client_modules/__init__.py
leo_1c/client_modules/bill_pdfs.py
leo_1c/client_modules/bills.py
leo_1c/client_modules/odata.py
leo_1c/client_modules/partners.py
leo_1c/entities/__init__.py
leo_1c/entities/bill.py
leo_1c/entities/entity.py
leo_1c/entities/partner.py
leo_1c-0.0.1.dist-info/LICENSE
leo_1c-0.0.1.dist-info/METADATA
leo_1c-0.0.1.dist-info/WHEEL
leo_1c-0.0.1.dist-info/top_level.txt
leo_1c-0.0.1.dist-info/RECORD
